MANIFEST.in
README.md
ardilla
setup.py
django_squirrell_materialize/__init__.py
django_squirrell_materialize.egg-info/PKG-INFO
django_squirrell_materialize.egg-info/SOURCES.txt
django_squirrell_materialize.egg-info/dependency_links.txt
django_squirrell_materialize.egg-info/top_level.txt
django_squirrell_materialize.egg-info/zip-safe
django_squirrell_materialize/static/admin/css/yourstyle.css
django_squirrell_materialize/static/admin/js/SelectBox.js
django_squirrell_materialize/static/admin/js/SelectFilter2.js
django_squirrell_materialize/static/admin/js/actions.js
django_squirrell_materialize/static/admin/js/actions.min.js
django_squirrell_materialize/static/admin/js/autocomplete.js
django_squirrell_materialize/static/admin/js/calendar.js
django_squirrell_materialize/static/admin/js/cancel.js
django_squirrell_materialize/static/admin/js/change_form.js
django_squirrell_materialize/static/admin/js/collapse.js
django_squirrell_materialize/static/admin/js/collapse.min.js
django_squirrell_materialize/static/admin/js/core.js
django_squirrell_materialize/static/admin/js/inlines.js
django_squirrell_materialize/static/admin/js/inlines.min.js
django_squirrell_materialize/static/admin/js/jquery.init.js
django_squirrell_materialize/static/admin/js/popup_response.js
django_squirrell_materialize/static/admin/js/prepopulate.js
django_squirrell_materialize/static/admin/js/prepopulate.min.js
django_squirrell_materialize/static/admin/js/prepopulate_init.js
django_squirrell_materialize/static/admin/js/timeparse.js
django_squirrell_materialize/static/admin/js/urlify.js
django_squirrell_materialize/static/admin/js/admin/DateTimeShortcuts.js
django_squirrell_materialize/static/admin/js/admin/RelatedObjectLookups.js
django_squirrell_materialize/static/admin/js/admin/main.js
django_squirrell_materialize/static/admin/js/vendor/__init__.py
django_squirrell_materialize/static/admin/js/vendor/jquery/jquery.js
django_squirrell_materialize/static/admin/js/vendor/jquery/jquery.min.js
django_squirrell_materialize/static/admin/js/vendor/select2/select2.full.js
django_squirrell_materialize/static/admin/js/vendor/select2/select2.full.min.js
django_squirrell_materialize/static/admin/js/vendor/select2/i18n/ar.js
