Metadata-Version: 2.1
Name: django-squirrell-materialize
Version: 1.4
Summary: A Docker and AWS utility package
Home-page: https://github.com/esco/django_ardilla_materialize
Author: ESCO
Author-email: franjcesco@gmail.com
License: UNKNOWN
Platform: UNKNOWN
Classifier: Programming Language :: Python :: 3
Classifier: License :: OSI Approved :: MIT License
Classifier: Operating System :: OS Independent
